[
     {
          "Bank Name":"Bank Rakyat",
          "Market Cap (US$ Billion)":"33.081"
     },
     {
          "Bank Name":"JPMorgan Chase",
          "Market Cap (US$ Billion)":"390.934"
     },
     {
          "Bank Name":"Industrial and Commercial Bank of China",
          "Market Cap (US$ Billion)":"345.214"
     },
     {
          "Bank Name":"Bank of America",
          "Market Cap (US$ Billion)":"325.331"
     },
     {
          "Bank Name":"Wells Fargo",
          "Market Cap (US$ Billion)":"308.013"
     },
     {
          "Bank Name":"China Construction Bank",
          "Market Cap (US$ Billion)":"257.399"
     },
     {
          "Bank Name":"HSBC Holdings PLC",
          "Market Cap (US$ Billion)":"219.270"
     },
     {
          "Bank Name":"Agricultural Bank of China",
          "Market Cap (US$ Billion)":"203.244"
     },
     {
          "Bank Name":"Citigroup Inc.",
          "Market Cap (US$ Billion)":"203.165"
     },
     {
          "Bank Name":"Bank of China",
          "Market Cap (US$ Billion)":"181.469"
     },
     {
          "Bank Name":"China Merchants Bank",
          "Market Cap (US$ Billion)":"122.616"
     },
     {
          "Bank Name":"Royal Bank of Canada",
          "Market Cap (US$ Billion)":"122.564"
     },
     {
          "Bank Name":"Banco Santander",
          "Market Cap (US$ Billion)":"115.696"
     },
     {
          "Bank Name":"Commonwealth Bank",
          "Market Cap (US$ Billion)":"112.227"
     },
     {
          "Bank Name":"Mitsubishi UFJ Financial Group",
          "Market Cap (US$ Billion)":"111.660"
     },
     {
          "Bank Name":"Toronto-Dominion Bank",
          "Market Cap (US$ Billion)":"108.449"
     },
     {
          "Bank Name":"BNP Paribas",
          "Market Cap (US$ Billion)":"103.258"
     },
     {
          "Bank Name":"Goldman Sachs",
          "Market Cap (US$ Billion)":"100.705"
     },
     {
          "Bank Name":"Sberbank of Russia",
          "Market Cap (US$ Billion)":"99.840"
     },
     {
          "Bank Name":"Morgan Stanley",
          "Market Cap (US$ Billion)":"99.651"
     },
     {
          "Bank Name":"U.S. Bancorp",
          "Market Cap (US$ Billion)":"94.558"
     },
     {
          "Bank Name":"HDFC Bank",
          "Market Cap (US$ Billion)":"100"
     },
     {
          "Bank Name":"Ita\u00fa Unibanco",
          "Market Cap (US$ Billion)":"86.203"
     },
     {
          "Bank Name":"Westpac",
          "Market Cap (US$ Billion)":"84.560"
     },
     {
          "Bank Name":"Scotiabank",
          "Market Cap (US$ Billion)":"78.947"
     },
     {
          "Bank Name":"ING Group",
          "Market Cap (US$ Billion)":"78.920"
     },
     {
          "Bank Name":"UBS",
          "Market Cap (US$ Billion)":"75.482"
     },
     {
          "Bank Name":"Charles Schwab",
          "Market Cap (US$ Billion)":"74.255"
     },
     {
          "Bank Name":"PNC Financial Services",
          "Market Cap (US$ Billion)":"72.246"
     },
     {
          "Bank Name":"Lloyds Banking Group",
          "Market Cap (US$ Billion)":"71.253"
     },
     {
          "Bank Name":"Sumitomo Mitsui Financial Group",
          "Market Cap (US$ Billion)":"67.328"
     },
     {
          "Bank Name":"Bank of Communications",
          "Market Cap (US$ Billion)":"67.078"
     },
     {
          "Bank Name":"Australia and New Zealand Banking Group",
          "Market Cap (US$ Billion)":"66.448"
     },
     {
          "Bank Name":"Banco Bradesco",
          "Market Cap (US$ Billion)":"64.816"
     },
     {
          "Bank Name":"National Australia Bank",
          "Market Cap (US$ Billion)":"63.794"
     },
     {
          "Bank Name":"Intesa Sanpaolo",
          "Market Cap (US$ Billion)":"62.032"
     },
     {
          "Bank Name":"Banco Bilbao Vizcaya Argentaria",
          "Market Cap (US$ Billion)":"60.678"
     },
     {
          "Bank Name":"Japan Post Bank",
          "Market Cap (US$ Billion)":"60.525"
     },
     {
          "Bank Name":"The Bank of New York Mellon",
          "Market Cap (US$ Billion)":"59.823"
     },
     {
          "Bank Name":"Shanghai Pudong Development Bank",
          "Market Cap (US$ Billion)":"58.796"
     },
     {
          "Bank Name":"Industrial Bank (China)",
          "Market Cap (US$ Billion)":"57.388"
     },
     {
          "Bank Name":"Bank of China (Hong Kong)",
          "Market Cap (US$ Billion)":"55.449"
     },
     {
          "Bank Name":"Bank of Montreal",
          "Market Cap (US$ Billion)":"53.181"
     },
     {
          "Bank Name":"Cr\u00e9dit Agricole",
          "Market Cap (US$ Billion)":"52.141"
     },
     {
          "Bank Name":"DBS Bank",
          "Market Cap (US$ Billion)":"51.475"
     },
     {
          "Bank Name":"Nordea",
          "Market Cap (US$ Billion)":"51.185"
     },
     {
          "Bank Name":"Capital One",
          "Market Cap (US$ Billion)":"51.107"
     },
     {
          "Bank Name":"Royal Bank of Scotland Group",
          "Market Cap (US$ Billion)":"50.490"
     },
     {
          "Bank Name":"Mizuho Financial Group",
          "Market Cap (US$ Billion)":"50.018"
     },
     {
          "Bank Name":"Credit Suisse",
          "Market Cap (US$ Billion)":"48.462"
     },
     {
          "Bank Name":"Postal Savings Bank of China",
          "Market Cap (US$ Billion)":"47.948"
     },
     {
          "Bank Name":"China Minsheng Bank",
          "Market Cap (US$ Billion)":"47.921"
     },
     {
          "Bank Name":"UniCredit",
          "Market Cap (US$ Billion)":"47.777"
     },
     {
          "Bank Name":"China CITIC Bank",
          "Market Cap (US$ Billion)":"47.451"
     },
     {
          "Bank Name":"Hang Seng Bank",
          "Market Cap (US$ Billion)":"46.171"
     },
     {
          "Bank Name":"Soci\u00e9t\u00e9 G\u00e9n\u00e9rale",
          "Market Cap (US$ Billion)":"46.051"
     },
     {
          "Bank Name":"Barclays",
          "Market Cap (US$ Billion)":"45.850"
     },
     {
          "Bank Name":"Canadian Imperial Bank of Commerce",
          "Market Cap (US$ Billion)":"43.544"
     },
     {
          "Bank Name":"Bank Central Asia",
          "Market Cap (US$ Billion)":"43.344"
     },
     {
          "Bank Name":"Truist Financial",
          "Market Cap (US$ Billion)":"41.923"
     },
     {
          "Bank Name":"Oversea-Chinese Banking Corp",
          "Market Cap (US$ Billion)":"41.362"
     },
     {
          "Bank Name":"State Bank of India",
          "Market Cap (US$ Billion)":"40.562"
     },
     {
          "Bank Name":"State Street",
          "Market Cap (US$ Billion)":"39.769"
     },
     {
          "Bank Name":"Deutsche Bank",
          "Market Cap (US$ Billion)":"38.649"
     },
     {
          "Bank Name":"KBC Bank",
          "Market Cap (US$ Billion)":"38.394"
     },
     {
          "Bank Name":"Danske Bank",
          "Market Cap (US$ Billion)":"38.223"
     },
     {
          "Bank Name":"Ping An Bank",
          "Market Cap (US$ Billion)":"37.993"
     },
     {
          "Bank Name":"Standard Chartered",
          "Market Cap (US$ Billion)":"37.319"
     },
     {
          "Bank Name":"United Overseas Bank",
          "Market Cap (US$ Billion)":"35.128"
     },
     {
          "Bank Name":"QNB Group",
          "Market Cap (US$ Billion)":"33.560"
     },
     {
          "Bank Name":"Bank Rakyat",
          "Market Cap (US$ Billion)":"33.081"
     }
]